[{"name":"java工程师","city":"南京-雨花台区","edu":"本科及以上","salary":"10-15k·16薪","experienceTime":"3-5年","age":"年龄不限","codeName":"语言不限"},{"name":"java工程师","city":"成都-高新区","edu":"本科及以上","salary":"10-15k·16薪","experienceTime":"3-5年","age":"年龄不限","codeName":"语言不限"},{"name":"java开发工程师","city":"厦门-后溪","edu":"本科及以上","salary":"10-15k·12薪","experienceTime":"1-3年","age":"年龄不限","codeName":"语言不限"},{"name":"Java中高级开发工程师（郑州）","city":"北京-来广营","edu":"本科及以上","salary":"10-15k·12薪","experienceTime":"3-5年","age":"年龄不限","codeName":"语言不限"},{"name":"高级Java开发工程师","city":"深圳","edu":"统招本科","salary":"25-35k·13薪","experienceTime":"5-10年","age":"年龄不限","codeName":"语言不限"},{"name":"高级Java研发工程师（大数据产品方向）","city":"上海","edu":"本科及以上","salary":"15-30k·13薪","experienceTime":"3-5年","age":"年龄不限","codeName":"语言不限"},{"name":"高级java工程师","city":"北京-朝阳区","edu":"本科及以上","salary":"18-30k·12薪","experienceTime":"5-10年","age":"年龄不限","codeName":"语言不限"},{"name":"Java工程师","city":"厦门-湖里区","edu":"本科及以上","salary":"面议","experienceTime":"1-3年","age":"20-30岁","codeName":"语言不限"},{"name":"Java","city":"苏州","edu":"本科及以上","salary":"10-15k·12薪","experienceTime":"3-5年","age":"年龄不限","codeName":"语言不限"},{"name":"java开发工程师","city":"杭州-西溪","edu":"本科及以上","salary":"13-18k·12薪","experienceTime":"3-5年","age":"年龄不限","codeName":"语言不限"},{"name":"Java技术","city":"长沙","edu":"本科及以上","salary":"8-12k·12薪","experienceTime":"1-3年","age":"年龄不限","codeName":"语言不限"},{"name":"应用开发工程师（Java）","city":"上海-徐汇区","edu":"本科及以上","salary":"15-25k·13薪","experienceTime":"3-5年","age":"年龄不限","codeName":"语言不限"},{"name":"java开发工程师","city":"北京-朝阳区","edu":"本科及以上","salary":"20-30k·15薪","experienceTime":"3-5年","age":"年龄不限","codeName":"语言不限"},{"name":"java开发工程师","city":"苏州-工业园区","edu":"本科及以上","salary":"20-30k·15薪","experienceTime":"3-5年","age":"年龄不限","codeName":"语言不限"},{"name":"java工程师","city":"上海","edu":"本科及以上","salary":"16-21k·12薪","experienceTime":"1-3年","age":"年龄不限","codeName":"语言不限"},{"name":"JAVA开发工程师（系统方向）","city":"上海-浦东新区","edu":"本科及以上","salary":"10-15k·14薪","experienceTime":"1-3年","age":"年龄不限","codeName":"语言不限"},{"name":"高级java开发工程师","city":"深圳-沙井","edu":"统招本科","salary":"17-25k·12薪","experienceTime":"5-10年","age":"25-35岁","codeName":"语言不限"},{"name":"中高级Java开发工程师","city":"广州-天河区","edu":"本科及以上","salary":"12-22k·12薪","experienceTime":"3-5年","age":"年龄不限","codeName":"语言不限"},{"name":"java软件工程师","city":"珠海-香洲区","edu":"大专及以上","salary":"13-17k·12薪","experienceTime":"3-5年","age":"年龄不限","codeName":"语言不限"},{"name":"Java Architect 应用架构师","city":"深圳-东门","edu":"本科及以上","salary":"30-40k·12薪","experienceTime":"5-10年","age":"年龄不限","codeName":"语言不限"},{"name":"高级java后端工程师G101975","city":"广州","edu":"本科及以上","salary":"12-20k·12薪","experienceTime":"1-3年","age":"年龄不限","codeName":"语言不限"},{"name":"资深java工程师","city":"北京-朝阳区","edu":"本科及以上","salary":"20-30k·12薪","experienceTime":"3-5年","age":"年龄不限","codeName":"语言不限"},{"name":"客户化开发工程师（JAVA，.NET）","city":"石家庄-长安区","edu":"本科及以上","salary":"5-10k·14薪","experienceTime":"1-3年","age":"年龄不限","codeName":"语言不限"},{"name":"java开发工程师","city":"佛山","edu":"本科及以上","salary":"8-12k·15薪","experienceTime":"1-3年","age":"年龄不限","codeName":"语言不限"},{"name":"JAVA开发工程师","city":"佛山","edu":"本科及以上","salary":"10-15k·14薪","experienceTime":"3-5年","age":"年龄不限","codeName":"语言不限"},{"name":"java软件工程师","city":"广州-越秀区","edu":"本科及以上","salary":"5-12k·12薪","experienceTime":"1-3年","age":"年龄不限","codeName":"语言不限"},{"name":"java高级软件工程师","city":"广州-越秀区","edu":"本科及以上","salary":"12-16k·12薪","experienceTime":"3-5年","age":"年龄不限","codeName":"语言不限"},{"name":"java开发工程师","city":"武汉-光谷","edu":"本科及以上","salary":"10-20k·12薪","experienceTime":"1-3年","age":"年龄不限","codeName":"语言不限"},{"name":"初中级java开发工程师","city":"长沙","edu":"大专及以上","salary":"5-8k·12薪","experienceTime":"1-3年","age":"年龄不限","codeName":"语言不限"},{"name":"高级java开发工程师","city":"广州-珠江新城","edu":"本科及以上","salary":"13-20k·13薪","experienceTime":"3-5年","age":"年龄不限","codeName":"语言不限"},{"name":"Java","city":"重庆","edu":"本科及以上","salary":"15-25k·12薪","experienceTime":"3-5年","age":"年龄不限","codeName":"语言不限"},{"name":"高级java开发工程师","city":"北京-牡丹园","edu":"统招本科","salary":"20-40k·12薪","experienceTime":"3-5年","age":"年龄不限","codeName":"语言不限"},{"name":"java开发工程师","city":"郑州-郑东新区","edu":"统招本科","salary":"8-10k·12薪","experienceTime":"1-3年","age":"年龄不限","codeName":"语言不限"},{"name":"Java开发工程师","city":"南京","edu":"大专及以上","salary":"10-15k·12薪","experienceTime":"3-5年","age":"年龄不限","codeName":"语言不限"},{"name":"java开发工程师","city":"北京","edu":"本科及以上","salary":"20-38k·12薪","experienceTime":"5-10年","age":"年龄不限","codeName":"语言不限"},{"name":"Java开发工程师（中/高级）","city":"北京-望京","edu":"本科及以上","salary":"15-30k·13薪","experienceTime":"5-10年","age":"年龄不限","codeName":"语言不限"},{"name":"java开发","city":"武汉-江夏区","edu":"统招本科","salary":"8-16k·12薪","experienceTime":"3-5年","age":"年龄不限","codeName":"语言不限"},{"name":"Java架构师","city":"北京","edu":"本科及以上","salary":"30-50k·12薪","experienceTime":"5-10年","age":"年龄不限","codeName":"普通话"},{"name":"java高级工程师","city":"成都-武侯区","edu":"本科及以上","salary":"20-40k·16薪","experienceTime":"经验不限","age":"年龄不限","codeName":"语言不限"},{"name":"大数据Java架构师","city":"北京","edu":"本科及以上","salary":"30-50k·12薪","experienceTime":"5-10年","age":"年龄不限","codeName":"普通话"}]