[{"name":"","city":"","edu":"","salary":"","experienceTime":"","age":"","jobUrl":"https://www.liepin.com/job/1932480083.shtml","codeName":""},{"name":"java开发工程师","city":"上海-静安区","edu":"统招本科","salary":"15-30k·15薪","experienceTime":"3-5年","age":"年龄不限","jobUrl":"https://www.liepin.com/job/1921992377.shtml","codeName":"语言不限"},{"name":"Java架构师","city":"南京-雨花台区","edu":"大专及以上","salary":"25-35k·14薪","experienceTime":"5-10年","age":"年龄不限","jobUrl":"https://www.liepin.com/job/1929328211.shtml","codeName":"语言不限"},{"name":"高级java开发工程师","city":"武汉","edu":"本科及以上","salary":"15-25k·14薪","experienceTime":"3-5年","age":"年龄不限","jobUrl":"https://www.liepin.com/job/1932474539.shtml","codeName":"语言不限"},{"name":"","city":"","edu":"","salary":"","experienceTime":"","age":"","jobUrl":"https://www.liepin.com/job/1930292735.shtml","codeName":""},{"name":"java技术经理","city":"深圳-科技园","edu":"统招本科","salary":"15-25k·12薪","experienceTime":"5-10年","age":"年龄不限","jobUrl":"https://www.liepin.com/job/1926129955.shtml","codeName":"语言不限"},{"name":"","city":"","edu":"","salary":"","experienceTime":"","age":"","jobUrl":"https://www.liepin.com/job/1930809167.shtml","codeName":""},{"name":"车联网-高级Java开发工程师/架构/全栈开发","city":"武汉","edu":"大专及以上","salary":"10-25k·13薪","experienceTime":"经验不限","age":"年龄不限","jobUrl":"https://www.liepin.com/job/1932673415.shtml","codeName":"语言不限"},{"name":"","city":"","edu":"","salary":"","experienceTime":"","age":"","jobUrl":"https://www.liepin.com/job/1932591633.shtml","codeName":""},{"name":"Java开发工程师","city":"杭州","edu":"统招本科","salary":"10-15k·12薪","experienceTime":"1-3年","age":"年龄不限","jobUrl":"https://www.liepin.com/job/1931688537.shtml","codeName":"语言不限"},{"name":"高级Java开发工程师","city":"杭州-西湖区","edu":"统招本科","salary":"12-15k·12薪","experienceTime":"3-5年","age":"年龄不限","jobUrl":"https://www.liepin.com/job/1931242257.shtml","codeName":"语言不限"},{"name":"高级java开发工程师","city":"深圳-大冲","edu":"本科及以上","salary":"25-35k·13薪","experienceTime":"3-5年","age":"年龄不限","jobUrl":"https://www.liepin.com/job/1930120299.shtml","codeName":"语言不限"},{"name":"java开发工程师","city":"贵阳-观山湖区","edu":"大专及以上","salary":"8-12k·12薪","experienceTime":"1-3年","age":"年龄不限","jobUrl":"https://www.liepin.com/job/1923320007.shtml","codeName":"语言不限"},{"name":"Java高级开发工程师","city":"北京-公主坟","edu":"本科及以上","salary":"16-20k·13薪","experienceTime":"5-10年","age":"年龄不限","jobUrl":"https://www.liepin.com/job/196636727.shtml","codeName":"英语 + 普通话"},{"name":"java开发工程师","city":"深圳-福田区","edu":"统招本科","salary":"16-20k·12薪","experienceTime":"经验不限","age":"25-35岁","jobUrl":"https://www.liepin.com/job/194885451.shtml","codeName":"普通话"},{"name":"","city":"","edu":"","salary":"","experienceTime":"","age":"","jobUrl":"https://www.liepin.com/job/1932599749.shtml","codeName":""},{"name":"高级java开发工程师","city":"杭州-西兴","edu":"本科及以上","salary":"14-30k·12薪","experienceTime":"3-5年","age":"年龄不限","jobUrl":"https://www.liepin.com/job/1932281615.shtml","codeName":"语言不限"},{"name":"Senior Java Developer","city":"北京-朝阳区","edu":"统招本科","salary":"面议","experienceTime":"5-10年","age":"30-40岁","jobUrl":"https://www.liepin.com/job/1932238585.shtml","codeName":"英语"},{"name":"资深Java开发工程师","city":"上海-塘桥","edu":"本科及以上","salary":"12-20k·12薪","experienceTime":"3-5年","age":"年龄不限","jobUrl":"https://www.liepin.com/job/1931637307.shtml","codeName":"语言不限"},{"name":"java开发工程师","city":"上海-虹桥","edu":"本科及以上","salary":"18-25k·12薪","experienceTime":"3-5年","age":"年龄不限","jobUrl":"https://www.liepin.com/job/1932631481.shtml","codeName":"语言不限"},{"name":"java架构师","city":"上海","edu":"统招本科","salary":"30-40k·12薪","experienceTime":"5-10年","age":"年龄不限","jobUrl":"https://www.liepin.com/job/1932524201.shtml","codeName":"语言不限"},{"name":"Java软件开发工程师","city":"北京","edu":"统招本科","salary":"20-30k·13薪","experienceTime":"5-10年","age":"年龄不限","jobUrl":"https://www.liepin.com/job/1931635425.shtml","codeName":"语言不限"},{"name":"","city":"","edu":"","salary":"","experienceTime":"","age":"","jobUrl":"https://www.liepin.com/job/1929419863.shtml","codeName":""},{"name":"","city":"","edu":"","salary":"","experienceTime":"","age":"","jobUrl":"https://www.liepin.com/job/1926568165.shtml","codeName":""},{"name":"java开发工程师","city":"北京-海淀区","edu":"统招本科","salary":"12-20k·14薪","experienceTime":"3-5年","age":"年龄不限","jobUrl":"https://www.liepin.com/job/1932613481.shtml","codeName":"语言不限"},{"name":"java开发工程师","city":"杭州","edu":"大专及以上","salary":"12-22k·12薪","experienceTime":"3-5年","age":"年龄不限","jobUrl":"https://www.liepin.com/job/1932606915.shtml","codeName":"语言不限"},{"name":"Java开发工程师（浦东驻场）","city":"上海-杨浦区","edu":"统招本科","salary":"12-20k·13薪","experienceTime":"3-5年","age":"年龄不限","jobUrl":"https://www.liepin.com/job/1925772891.shtml","codeName":"语言不限"},{"name":"Java开发工程师","city":"深圳-南山区","edu":"硕士及以上","salary":"20-30k·12薪","experienceTime":"3-5年","age":"年龄不限","jobUrl":"https://www.liepin.com/job/1920303707.shtml","codeName":"语言不限"},{"name":"高级java开发工程师","city":"深圳-福田区","edu":"本科及以上","salary":"16-30k·12薪","experienceTime":"5-10年","age":"年龄不限","jobUrl":"https://www.liepin.com/job/1931698577.shtml","codeName":"语言不限"},{"name":"高级Java开发工程师","city":"南京-建邺区","edu":"本科及以上","salary":"10-18k·12薪","experienceTime":"1-3年","age":"年龄不限","jobUrl":"https://www.liepin.com/job/1931637161.shtml","codeName":"语言不限"},{"name":"","city":"","edu":"","salary":"","experienceTime":"","age":"","jobUrl":"https://www.liepin.com/job/1924194927.shtml","codeName":""},{"name":"高级Java开发工程师（小微事业部）","city":"南京-建邺区","edu":"统招本科","salary":"15-20k·12薪","experienceTime":"3-5年","age":"年龄不限","jobUrl":"https://www.liepin.com/job/1932245401.shtml","codeName":"语言不限"},{"name":"JAVA开发工程师岗","city":"上海","edu":"统招本科","salary":"15-25k·12薪","experienceTime":"1-3年","age":"年龄不限","jobUrl":"https://www.liepin.com/job/1928432175.shtml","codeName":"语言不限"},{"name":"","city":"","edu":"","salary":"","experienceTime":"","age":"","jobUrl":"https://www.liepin.com/job/1932346671.shtml","codeName":""},{"name":"","city":"","edu":"","salary":"","experienceTime":"","age":"","jobUrl":"https://www.liepin.com/job/1915514242.shtml","codeName":""},{"name":"","city":"","edu":"","salary":"","experienceTime":"","age":"","jobUrl":"https://www.liepin.com/job/1927533377.shtml","codeName":""},{"name":"","city":"","edu":"","salary":"","experienceTime":"","age":"","jobUrl":"https://www.liepin.com/job/1931208013.shtml","codeName":""},{"name":"","city":"","edu":"","salary":"","experienceTime":"","age":"","jobUrl":"https://www.liepin.com/job/1927837553.shtml","codeName":""},{"name":"Java开发工程师","city":"广州-花都区","edu":"大专及以上","salary":"10-18k·12薪","experienceTime":"3-5年","age":"年龄不限","jobUrl":"https://www.liepin.com/job/1930500923.shtml","codeName":"语言不限"},{"name":"中级JAVA工程师","city":"成都-双流区","edu":"统招本科","salary":"面议","experienceTime":"3-5年","age":"年龄不限","jobUrl":"https://www.liepin.com/job/1928355189.shtml","codeName":"语言不限"},{"name":"java开发工程师","city":"深圳-龙岗区","edu":"本科及以上","salary":"15-20k·12薪","experienceTime":"3-5年","age":"年龄不限","jobUrl":"https://www.liepin.com/job/1932689661.shtml","codeName":"语言不限"},{"name":"JAVA开发工程师-六朝云商圈-南京","city":"南京","edu":"本科及以上","salary":"10-15k·12薪","experienceTime":"3-5年","age":"年龄不限","jobUrl":"https://www.liepin.com/job/1932689471.shtml","codeName":"语言不限"},{"name":"","city":"","edu":"","salary":"","experienceTime":"","age":"","jobUrl":"https://www.liepin.com/job/1932689099.shtml","codeName":""},{"name":"java开发工程师","city":"杭州-西溪","edu":"统招本科","salary":"23-45k·15薪","experienceTime":"3-5年","age":"年龄不限","jobUrl":"https://www.liepin.com/job/1932688515.shtml","codeName":"语言不限"},{"name":"Java研发工程师-上海","city":"上海-浦东新区","edu":"统招本科","salary":"15-25k·12薪","experienceTime":"3-5年","age":"年龄不限","jobUrl":"https://www.liepin.com/job/1932688477.shtml","codeName":"语言不限"},{"name":"高级java工程师","city":"北京-大兴区","edu":"本科及以上","salary":"20-40k·13薪","experienceTime":"3-5年","age":"年龄不限","jobUrl":"https://www.liepin.com/job/1932688327.shtml","codeName":"语言不限"},{"name":"Java（银行方向）","city":"上海-浦东新区","edu":"本科及以上","salary":"13-16k·12薪","experienceTime":"3-5年","age":"年龄不限","jobUrl":"https://www.liepin.com/job/1932688175.shtml","codeName":"语言不限"},{"name":"Java开发工程师（高级）","city":"武汉-东西湖区","edu":"统招本科","salary":"10-18k·12薪","experienceTime":"3-5年","age":"年龄不限","jobUrl":"https://www.liepin.com/job/1932688029.shtml","codeName":"语言不限"},{"name":"java开发工程师","city":"北京-海淀区","edu":"本科及以上","salary":"10-20k·12薪","experienceTime":"3-5年","age":"年龄不限","jobUrl":"https://www.liepin.com/job/1932687987.shtml","codeName":"语言不限"},{"name":"java开发工程师","city":"上海","edu":"本科及以上","salary":"10-15k·12薪","experienceTime":"1-3年","age":"年龄不限","jobUrl":"https://www.liepin.com/job/1932687445.shtml","codeName":"语言不限"},{"name":"","city":"","edu":"","salary":"","experienceTime":"","age":"","jobUrl":"https://www.liepin.com/job/1932687287.shtml","codeName":""},{"name":"到店到综技术部-Java开发-餐饮线（杭州、上海）","city":"杭州","edu":"学历不限","salary":"面议","experienceTime":"5-10年","age":"年龄不限","jobUrl":"https://www.liepin.com/job/1932687269.shtml","codeName":"语言不限"},{"name":"IT部—软件开发（Java）","city":"北京","edu":"本科及以上","salary":"12-15k·12薪","experienceTime":"3-5年","age":"年龄不限","jobUrl":"https://www.liepin.com/job/1932687195.shtml","codeName":"语言不限"},{"name":"","city":"","edu":"","salary":"","experienceTime":"","age":"","jobUrl":"https://www.liepin.com/job/1932686941.shtml","codeName":""},{"name":"java服务器开发工程师","city":"北京-大红门","edu":"本科及以上","salary":"18-25k·13薪","experienceTime":"3-5年","age":"年龄不限","jobUrl":"https://www.liepin.com/job/1932686939.shtml","codeName":"语言不限"},{"name":"初级Java开发工程师（外汇岗位）","city":"上海-浦东新区","edu":"本科及以上","salary":"9-16k·12薪","experienceTime":"1-3年","age":"年龄不限","jobUrl":"https://www.liepin.com/job/1932686821.shtml","codeName":"语言不限"},{"name":"中级Java开发工程师（外汇岗位）","city":"上海-浦东新区","edu":"大专及以上","salary":"13-18k·12薪","experienceTime":"3-5年","age":"年龄不限","jobUrl":"https://www.liepin.com/job/1932686809.shtml","codeName":"语言不限"},{"name":"高级Java开发工程师（外汇岗位）","city":"上海-浦东新区","edu":"大专及以上","salary":"18-25k·12薪","experienceTime":"5-10年","age":"年龄不限","jobUrl":"https://www.liepin.com/job/1932686791.shtml","codeName":"语言不限"},{"name":"Java架构师","city":"上海-浦东新区","edu":"大专及以上","salary":"25-35k·12薪","experienceTime":"5-10年","age":"年龄不限","jobUrl":"https://www.liepin.com/job/1932686771.shtml","codeName":"语言不限"},{"name":"Java开发主管","city":"上海-浦东新区","edu":"本科及以上","salary":"25-30k·12薪","experienceTime":"5-10年","age":"年龄不限","jobUrl":"https://www.liepin.com/job/1932686751.shtml","codeName":"语言不限"},{"name":"港股上市供应链金融企业--java开发经理/架构师","city":"深圳","edu":"本科及以上","salary":"41-83k·16薪","experienceTime":"经验不限","age":"年龄不限","jobUrl":"https://www.liepin.com/job/1932686711.shtml","codeName":"语言不限"},{"name":"Java研发工程师","city":"长沙-岳麓区","edu":"统招本科","salary":"面议","experienceTime":"5-10年","age":"年龄不限","jobUrl":"https://www.liepin.com/job/1932686315.shtml","codeName":"语言不限"},{"name":"","city":"","edu":"","salary":"","experienceTime":"","age":"","jobUrl":"https://www.liepin.com/job/1932686195.shtml","codeName":""},{"name":"","city":"","edu":"","salary":"","experienceTime":"","age":"","jobUrl":"https://www.liepin.com/job/1932686137.shtml","codeName":""},{"name":"Java开发工程师","city":"深圳","edu":"本科及以上","salary":"8-15k·12薪","experienceTime":"1-3年","age":"年龄不限","jobUrl":"https://www.liepin.com/job/1932685845.shtml","codeName":"语言不限"},{"name":"","city":"","edu":"","salary":"","experienceTime":"","age":"","jobUrl":"https://www.liepin.com/job/1932685093.shtml","codeName":""},{"name":"","city":"","edu":"","salary":"","experienceTime":"","age":"","jobUrl":"https://www.liepin.com/job/1932685087.shtml","codeName":""},{"name":"","city":"","edu":"","salary":"","experienceTime":"","age":"","jobUrl":"https://www.liepin.com/job/1932684939.shtml","codeName":""},{"name":"","city":"","edu":"","salary":"","experienceTime":"","age":"","jobUrl":"https://www.liepin.com/job/1932684343.shtml","codeName":""},{"name":"高级java工程师","city":"北京","edu":"统招本科","salary":"20-30k·12薪","experienceTime":"5-10年","age":"20-35岁","jobUrl":"https://www.liepin.com/job/1932684261.shtml","codeName":"语言不限"},{"name":"高级Java架构师","city":"北京","edu":"统招本科","salary":"20-35k·12薪","experienceTime":"5-10年","age":"20-35岁","jobUrl":"https://www.liepin.com/job/1932684131.shtml","codeName":"语言不限"},{"name":"java开发工程师","city":"武汉-江汉区","edu":"大专及以上","salary":"10-15k·12薪","experienceTime":"3-5年","age":"年龄不限","jobUrl":"https://www.liepin.com/job/1932684097.shtml","codeName":"语言不限"},{"name":"高级java开发工程师","city":"上海-徐汇区","edu":"本科及以上","salary":"20-30k·16薪","experienceTime":"3-5年","age":"年龄不限","jobUrl":"https://www.liepin.com/job/1932684017.shtml","codeName":"语言不限"},{"name":"","city":"","edu":"","salary":"","experienceTime":"","age":"","jobUrl":"https://www.liepin.com/job/1932683803.shtml","codeName":""},{"name":"","city":"","edu":"","salary":"","experienceTime":"","age":"","jobUrl":"https://www.liepin.com/job/1932683655.shtml","codeName":""},{"name":"JAVA研发工程师","city":"成都","edu":"大专及以上","salary":"10-20k·12薪","experienceTime":"1-3年","age":"年龄不限","jobUrl":"https://www.liepin.com/job/1932683219.shtml","codeName":"语言不限"},{"name":"高级java开发工程师","city":"杭州-古荡","edu":"本科及以上","salary":"20-30k·16薪","experienceTime":"3-5年","age":"年龄不限","jobUrl":"https://www.liepin.com/job/1932682919.shtml","codeName":"语言不限"},{"name":"软件开发岗-Java开发工程师（中级）","city":"广州-天河区","edu":"统招本科","salary":"10-30k·12薪","experienceTime":"3-5年","age":"年龄不限","jobUrl":"https://www.liepin.com/job/1932682733.shtml","codeName":"语言不限"},{"name":"高级java开发工程师","city":"广州-黄埔区","edu":"本科及以上","salary":"16-28k·12薪","experienceTime":"5-10年","age":"年龄不限","jobUrl":"https://www.liepin.com/job/1932682213.shtml","codeName":"语言不限"},{"name":"","city":"","edu":"","salary":"","experienceTime":"","age":"","jobUrl":"https://www.liepin.com/job/1932682175.shtml","codeName":""},{"name":"","city":"","edu":"","salary":"","experienceTime":"","age":"","jobUrl":"https://www.liepin.com/job/1932676939.shtml","codeName":""},{"name":"Java","city":"杭州","edu":"本科及以上","salary":"20-30k·12薪","experienceTime":"3-5年","age":"年龄不限","jobUrl":"https://www.liepin.com/job/1932676809.shtml","codeName":"语言不限"},{"name":"","city":"","edu":"","salary":"","experienceTime":"","age":"","jobUrl":"https://www.liepin.com/job/1932676801.shtml","codeName":""},{"name":"","city":"","edu":"","salary":"","experienceTime":"","age":"","jobUrl":"https://www.liepin.com/job/1932676783.shtml","codeName":""},{"name":"java-api","city":"北京","edu":"统招本科","salary":"17-30k·15薪","experienceTime":"3-5年","age":"年龄不限","jobUrl":"https://www.liepin.com/job/1932676661.shtml","codeName":"语言不限"},{"name":"","city":"","edu":"","salary":"","experienceTime":"","age":"","jobUrl":"https://www.liepin.com/job/1932676511.shtml","codeName":""},{"name":"java高级开发，后端服务","city":"北京","edu":"统招本科","salary":"15-25k·16薪","experienceTime":"5-10年","age":"年龄不限","jobUrl":"https://www.liepin.com/job/1932676129.shtml","codeName":"语言不限"},{"name":"","city":"","edu":"","salary":"","experienceTime":"","age":"","jobUrl":"https://www.liepin.com/job/1932675743.shtml","codeName":""},{"name":"Java","city":"北京","edu":"统招本科","salary":"16-25k·16薪","experienceTime":"5-10年","age":"年龄不限","jobUrl":"https://www.liepin.com/job/1932675687.shtml","codeName":"语言不限"},{"name":"","city":"","edu":"","salary":"","experienceTime":"","age":"","jobUrl":"https://www.liepin.com/job/1932675357.shtml","codeName":""},{"name":"","city":"","edu":"","salary":"","experienceTime":"","age":"","jobUrl":"https://www.liepin.com/job/1932675355.shtml","codeName":""},{"name":"java开发工程师","city":"北京-朝阳区","edu":"本科及以上","salary":"25-30k·12薪","experienceTime":"5-10年","age":"年龄不限","jobUrl":"https://www.liepin.com/job/1932674989.shtml","codeName":"语言不限"},{"name":"","city":"","edu":"","salary":"","experienceTime":"","age":"","jobUrl":"https://www.liepin.com/job/1932674973.shtml","codeName":""},{"name":"高级java开发工程师","city":"北京-大兴区","edu":"统招本科","salary":"20-40k·14薪","experienceTime":"5-10年","age":"25-35岁","jobUrl":"https://www.liepin.com/job/1932674855.shtml","codeName":"语言不限"},{"name":"Application Support（Python+Java）","city":"上海-金桥","edu":"本科及以上","salary":"22-25k·13薪","experienceTime":"5-10年","age":"年龄不限","jobUrl":"https://www.liepin.com/job/1932674811.shtml","codeName":"语言不限"},{"name":"java工程师","city":"杭州-古荡","edu":"本科及以上","salary":"7-11k·12薪","experienceTime":"1-3年","age":"年龄不限","jobUrl":"https://www.liepin.com/job/1932674585.shtml","codeName":"语言不限"},{"name":"java开发","city":"北京-东城区","edu":"本科及以上","salary":"10-25k·12薪","experienceTime":"3-5年","age":"年龄不限","jobUrl":"https://www.liepin.com/job/1932674445.shtml","codeName":"语言不限"},{"name":"","city":"","edu":"","salary":"","experienceTime":"","age":"","jobUrl":"https://www.liepin.com/job/1932674083.shtml","codeName":""},{"name":"","city":"","edu":"","salary":"","experienceTime":"","age":"","jobUrl":"https://www.liepin.com/job/1932674045.shtml","codeName":""},{"name":"Java开发工程师","city":"上海","edu":"本科及以上","salary":"15-25k·12薪","experienceTime":"3-5年","age":"年龄不限","jobUrl":"https://www.liepin.com/job/1932673879.shtml","codeName":"语言不限"},{"name":"Java","city":"北京-昌平区","edu":"本科及以上","salary":"11-22k·13薪","experienceTime":"1-3年","age":"年龄不限","jobUrl":"https://www.liepin.com/job/1932673747.shtml","codeName":"语言不限"},{"name":"java技术经理","city":"广州-天河区","edu":"大专及以上","salary":"20-30k·12薪","experienceTime":"5-10年","age":"年龄不限","jobUrl":"https://www.liepin.com/job/1932673657.shtml","codeName":"语言不限"},{"name":"java开发工程师","city":"北京-东城区","edu":"本科及以上","salary":"1-2k·12薪","experienceTime":"1-3年","age":"年龄不限","jobUrl":"https://www.liepin.com/job/1932673655.shtml","codeName":"语言不限"},{"name":"软件开发工程师(Java)","city":"上海-中山公园","edu":"本科及以上","salary":"13-20k·15薪","experienceTime":"3-5年","age":"年龄不限","jobUrl":"https://www.liepin.com/job/1932672345.shtml","codeName":"语言不限"},{"name":"【推荐搜索平台】高级Java开发工程师","city":"上海","edu":"本科及以上","salary":"30-45k·16薪","experienceTime":"3-5年","age":"年龄不限","jobUrl":"https://www.liepin.com/job/1932672255.shtml","codeName":"语言不限"},{"name":"JAVA高级开发工程师(J201016003)","city":"杭州","edu":"本科及以上","salary":"25-46k·12薪","experienceTime":"1-3年","age":"年龄不限","jobUrl":"https://www.liepin.com/job/1932672131.shtml","codeName":"语言不限"},{"name":"java软件工程师","city":"天津","edu":"大专及以上","salary":"6-11k·12薪","experienceTime":"1-3年","age":"年龄不限","jobUrl":"https://www.liepin.com/job/1932672095.shtml","codeName":"语言不限"},{"name":"中级java开发工程师","city":"杭州","edu":"统招本科","salary":"15-20k·14薪","experienceTime":"3-5年","age":"年龄不限","jobUrl":"https://www.liepin.com/job/1932672079.shtml","codeName":"语言不限"},{"name":"","city":"","edu":"","salary":"","experienceTime":"","age":"","jobUrl":"https://www.liepin.com/job/1932671889.shtml","codeName":""},{"name":"高级java/scala开发工程师（启明）","city":"广州-海珠区","edu":"统招本科","salary":"20-30k·15薪","experienceTime":"3-5年","age":"年龄不限","jobUrl":"https://www.liepin.com/job/1932671541.shtml","codeName":"语言不限"},{"name":"高级java开发工程师（底层交易平台）","city":"广州-海珠区","edu":"统招本科","salary":"20-30k·15薪","experienceTime":"3-5年","age":"年龄不限","jobUrl":"https://www.liepin.com/job/1932671485.shtml","codeName":"语言不限"},{"name":"java开发实习生","city":"长沙-岳麓区","edu":"统招本科","salary":"2-3k·12薪","experienceTime":"经验不限","age":"年龄不限","jobUrl":"https://www.liepin.com/job/1932671115.shtml","codeName":"语言不限"},{"name":"java软件工程师","city":"成都","edu":"本科及以上","salary":"15-25k·15薪","experienceTime":"1-3年","age":"年龄不限","jobUrl":"https://www.liepin.com/job/1932670997.shtml","codeName":"语言不限"},{"name":"java开发工程师","city":"石家庄","edu":"统招本科","salary":"12-18k·12薪","experienceTime":"3-5年","age":"年龄不限","jobUrl":"https://www.liepin.com/job/1932670767.shtml","codeName":"语言不限"},{"name":"","city":"","edu":"","salary":"","experienceTime":"","age":"","jobUrl":"https://www.liepin.com/job/1932670733.shtml","codeName":""},{"name":"Java开发工程师","city":"成都","edu":"统招本科","salary":"10-15k·12薪","experienceTime":"1-3年","age":"年龄不限","jobUrl":"https://www.liepin.com/job/1932670303.shtml","codeName":"语言不限"},{"name":"","city":"","edu":"","salary":"","experienceTime":"","age":"","jobUrl":"https://www.liepin.com/job/1932670085.shtml","codeName":""},{"name":"高薪聘Java技术/程序员","city":"邢台","edu":"本科及以上","salary":"20-30k·12薪","experienceTime":"3-5年","age":"年龄不限","jobUrl":"https://www.liepin.com/job/1932670045.shtml","codeName":"语言不限"},{"name":"","city":"","edu":"","salary":"","experienceTime":"","age":"","jobUrl":"https://www.liepin.com/job/1932669887.shtml","codeName":""},{"name":"java开发工程师","city":"北京-海淀区","edu":"本科及以上","salary":"14-18k·12薪","experienceTime":"5-10年","age":"年龄不限","jobUrl":"https://www.liepin.com/job/1932669779.shtml","codeName":"语言不限"},{"name":"java开发工程师","city":"重庆","edu":"本科及以上","salary":"11-22k·13薪","experienceTime":"经验不限","age":"年龄不限","jobUrl":"https://www.liepin.com/job/1932663797.shtml","codeName":"语言不限"},{"name":"","city":"","edu":"","salary":"","experienceTime":"","age":"","jobUrl":"https://www.liepin.com/job/1932663795.shtml","codeName":""},{"name":"java开发工程师","city":"苏州","edu":"本科及以上","salary":"11-22k·13薪","experienceTime":"经验不限","age":"年龄不限","jobUrl":"https://www.liepin.com/job/1932663793.shtml","codeName":"语言不限"},{"name":"java开发工程师","city":"北京","edu":"本科及以上","salary":"11-22k·13薪","experienceTime":"经验不限","age":"年龄不限","jobUrl":"https://www.liepin.com/job/1932663791.shtml","codeName":"语言不限"},{"name":"高级java工程师 (MJ001724)","city":"厦门-莲前","edu":"统招本科","salary":"20-30k·12薪","experienceTime":"3-5年","age":"年龄不限","jobUrl":"https://www.liepin.com/job/1932663691.shtml","codeName":"语言不限"},{"name":"","city":"","edu":"","salary":"","experienceTime":"","age":"","jobUrl":"https://www.liepin.com/job/1932663599.shtml","codeName":""},{"name":"","city":"","edu":"","salary":"","experienceTime":"","age":"","jobUrl":"https://www.liepin.com/job/1932663571.shtml","codeName":""},{"name":"java中级开发工程师(非外包+上市公司）","city":"成都-高新区","edu":"统招本科","salary":"13-18k·12薪","experienceTime":"3-5年","age":"年龄不限","jobUrl":"https://www.liepin.com/job/1932663549.shtml","codeName":"语言不限"},{"name":"","city":"","edu":"","salary":"","experienceTime":"","age":"","jobUrl":"https://www.liepin.com/job/1932663399.shtml","codeName":""},{"name":"Java全栈开发（自研产品+非外包+上市公司）","city":"成都-高新区","edu":"本科及以上","salary":"12-18k·12薪","experienceTime":"3-5年","age":"年龄不限","jobUrl":"https://www.liepin.com/job/1932663239.shtml","codeName":"语言不限"},{"name":"","city":"","edu":"","salary":"","experienceTime":"","age":"","jobUrl":"https://www.liepin.com/job/1932662879.shtml","codeName":""},{"name":"java后台开发工程师","city":"保定","edu":"统招本科","salary":"10-25k·13薪","experienceTime":"3-5年","age":"年龄不限","jobUrl":"https://www.liepin.com/job/1932662863.shtml","codeName":"语言不限"},{"name":"","city":"","edu":"","salary":"","experienceTime":"","age":"","jobUrl":"https://www.liepin.com/job/1932662795.shtml","codeName":""},{"name":"Java","city":"东莞-长安镇","edu":"大专及以上","salary":"15-18k·12薪","experienceTime":"3-5年","age":"年龄不限","jobUrl":"https://www.liepin.com/job/1932662761.shtml","codeName":"语言不限"},{"name":"","city":"","edu":"","salary":"","experienceTime":"","age":"","jobUrl":"https://www.liepin.com/job/1932662753.shtml","codeName":""},{"name":"Java","city":"长春-南关区","edu":"本科及以上","salary":"12-15k·12薪","experienceTime":"3-5年","age":"年龄不限","jobUrl":"https://www.liepin.com/job/1932662489.shtml","codeName":"语言不限"},{"name":"java开发工程师","city":"郑州-新密","edu":"大专及以上","salary":"3-5k·12薪","experienceTime":"3-5年","age":"年龄不限","jobUrl":"https://www.liepin.com/job/1932661661.shtml","codeName":"语言不限"},{"name":"","city":"","edu":"","salary":"","experienceTime":"","age":"","jobUrl":"https://www.liepin.com/job/1932661651.shtml","codeName":""},{"name":"中级java开发工程师","city":"西安-雁塔区","edu":"本科及以上","salary":"12-20k·12薪","experienceTime":"3-5年","age":"年龄不限","jobUrl":"https://www.liepin.com/job/1932661269.shtml","codeName":"语言不限"},{"name":"java开发工程师","city":"昆明","edu":"本科及以上","salary":"9-13k·12薪","experienceTime":"1-3年","age":"年龄不限","jobUrl":"https://www.liepin.com/job/1932661249.shtml","codeName":"语言不限"},{"name":"","city":"","edu":"","salary":"","experienceTime":"","age":"","jobUrl":"https://www.liepin.com/job/1932660863.shtml","codeName":""},{"name":"","city":"","edu":"","salary":"","experienceTime":"","age":"","jobUrl":"https://www.liepin.com/job/1932659999.shtml","codeName":""},{"name":"Java高级研发、技术专家","city":"杭州","edu":"本科及以上","salary":"30-55k·12薪","experienceTime":"5-10年","age":"年龄不限","jobUrl":"https://www.liepin.com/job/1932659997.shtml","codeName":"普通话"},{"name":"Java中级开发工程师","city":"西安","edu":"本科及以上","salary":"8-15k·12薪","experienceTime":"5-10年","age":"年龄不限","jobUrl":"https://www.liepin.com/job/1932659879.shtml","codeName":"普通话"},{"name":"java工程师","city":"苏州-工业园区","edu":"大专及以上","salary":"9-13k·12薪","experienceTime":"5-10年","age":"年龄不限","jobUrl":"https://www.liepin.com/job/1932659709.shtml","codeName":"普通话"},{"name":"Java开发工程师","city":"武汉","edu":"本科及以上","salary":"6-8k·12薪","experienceTime":"经验不限","age":"年龄不限","jobUrl":"https://www.liepin.com/job/1932659441.shtml","codeName":"普通话"},{"name":"高级JAVA开发工程师","city":"上海","edu":"本科及以上","salary":"10-20k·12薪","experienceTime":"5-10年","age":"年龄不限","jobUrl":"https://www.liepin.com/job/1932659059.shtml","codeName":"普通话"},{"name":"Android开发/JAVA开发","city":"杭州","edu":"学历不限","salary":"15-25k·12薪","experienceTime":"经验不限","age":"年龄不限","jobUrl":"https://www.liepin.com/job/1932658499.shtml","codeName":"普通话"},{"name":"","city":"","edu":"","salary":"","experienceTime":"","age":"","jobUrl":"https://www.liepin.com/job/1932658297.shtml","codeName":""},{"name":"Java开发工程师","city":"北京-朝阳区","edu":"本科及以上","salary":"15-30k·12薪","experienceTime":"5-10年","age":"年龄不限","jobUrl":"https://www.liepin.com/job/1932657835.shtml","codeName":"普通话"},{"name":"高级java开发工程师","city":"武汉","edu":"本科及以上","salary":"12-18k·12薪","experienceTime":"5-10年","age":"年龄不限","jobUrl":"https://www.liepin.com/job/1932657805.shtml","codeName":"普通话"},{"name":"","city":"","edu":"","salary":"","experienceTime":"","age":"","jobUrl":"https://www.liepin.com/job/1932657309.shtml","codeName":""},{"name":"","city":"","edu":"","salary":"","experienceTime":"","age":"","jobUrl":"https://www.liepin.com/job/1932656817.shtml","codeName":""},{"name":"高级JAVA工程师","city":"北京","edu":"本科及以上","salary":"20-40k·12薪","experienceTime":"5-10年","age":"年龄不限","jobUrl":"https://www.liepin.com/job/1932656577.shtml","codeName":"普通话"},{"name":"java研发主管","city":"上海-漕河泾","edu":"本科及以上","salary":"15-22k·14薪","experienceTime":"5-10年","age":"年龄不限","jobUrl":"https://www.liepin.com/job/1932656075.shtml","codeName":"语言不限"},{"name":"","city":"","edu":"","salary":"","experienceTime":"","age":"","jobUrl":"https://www.liepin.com/job/1932656041.shtml","codeName":""},{"name":"","city":"","edu":"","salary":"","experienceTime":"","age":"","jobUrl":"https://www.liepin.com/job/1932656039.shtml","codeName":""},{"name":"Java开发前端","city":"南京-江东","edu":"本科及以上","salary":"13-18k·12薪","experienceTime":"1-3年","age":"年龄不限","jobUrl":"https://www.liepin.com/job/1932655093.shtml","codeName":"语言不限"},{"name":"","city":"","edu":"","salary":"","experienceTime":"","age":"","jobUrl":"https://www.liepin.com/job/1932651035.shtml","codeName":""},{"name":"java开发工程师（往培养架构师）","city":"深圳-南山区","edu":"统招本科","salary":"15-25k·15薪","experienceTime":"3-5年","age":"年龄不限","jobUrl":"https://www.liepin.com/job/1932648909.shtml","codeName":"语言不限"},{"name":"JAVA开发工程师(J201009094)","city":"北京-海淀区","edu":"本科及以上","salary":"25-50k·12薪","experienceTime":"3-5年","age":"年龄不限","jobUrl":"https://www.liepin.com/job/1932648811.shtml","codeName":"语言不限"},{"name":"Application Developer - Java","city":"大连","edu":"本科及以上","salary":"10-30k·13薪","experienceTime":"5-10年","age":"年龄不限","jobUrl":"https://www.liepin.com/job/1932648117.shtml","codeName":"语言不限"},{"name":"Application Developer - Java - Japanese","city":"大连","edu":"本科及以上","salary":"10-30k·13薪","experienceTime":"5-10年","age":"年龄不限","jobUrl":"https://www.liepin.com/job/1932647997.shtml","codeName":"语言不限"},{"name":"ERP技术开发/Java开发顾问","city":"上海-徐汇区","edu":"大专及以上","salary":"10-15k·12薪","experienceTime":"3-5年","age":"年龄不限","jobUrl":"https://www.liepin.com/job/1932645713.shtml","codeName":"语言不限"},{"name":"","city":"","edu":"","salary":"","experienceTime":"","age":"","jobUrl":"https://www.liepin.com/job/1932645395.shtml","codeName":""},{"name":"","city":"","edu":"","salary":"","experienceTime":"","age":"","jobUrl":"https://www.liepin.com/job/1932643873.shtml","codeName":""},{"name":"","city":"","edu":"","salary":"","experienceTime":"","age":"","jobUrl":"https://www.liepin.com/job/1932643431.shtml","codeName":""},{"name":"Java开发工程师 (NJ-HS-D001)","city":"南京-秦淮区","edu":"大专及以上","salary":"8-16k·12薪","experienceTime":"1-3年","age":"年龄不限","jobUrl":"https://www.liepin.com/job/1932641841.shtml","codeName":"语言不限"},{"name":"","city":"","edu":"","salary":"","experienceTime":"","age":"","jobUrl":"https://www.liepin.com/job/1932640917.shtml","codeName":""},{"name":"Java开发工程师-常州","city":"常州-文化宫","edu":"统招本科","salary":"8-20k·12薪","experienceTime":"1-3年","age":"年龄不限","jobUrl":"https://www.liepin.com/job/1932637105.shtml","codeName":"语言不限"},{"name":"","city":"","edu":"","salary":"","experienceTime":"","age":"","jobUrl":"https://www.liepin.com/job/1932636855.shtml","codeName":""},{"name":"","city":"","edu":"","salary":"","experienceTime":"","age":"","jobUrl":"https://www.liepin.com/job/1932636725.shtml","codeName":""},{"name":"java开发工程师-运营商BU-合肥","city":"合肥-高新区","edu":"统招本科","salary":"15-20k·14薪","experienceTime":"5-10年","age":"年龄不限","jobUrl":"https://www.liepin.com/job/1932636487.shtml","codeName":"语言不限"},{"name":"Java开发工程师","city":"南京","edu":"大专及以上","salary":"12-22k·12薪","experienceTime":"5-10年","age":"年龄不限","jobUrl":"https://www.liepin.com/job/1932632989.shtml","codeName":"普通话"},{"name":"资深 Java 软件工程师","city":"上海","edu":"本科及以上","salary":"20-28k·12薪","experienceTime":"5-10年","age":"年龄不限","jobUrl":"https://www.liepin.com/job/1932632781.shtml","codeName":"语言不限"},{"name":"java开发工程师","city":"深圳-南山区","edu":"本科及以上","salary":"20-30k·12薪","experienceTime":"3-5年","age":"年龄不限","jobUrl":"https://www.liepin.com/job/1932632777.shtml","codeName":"语言不限"},{"name":"Java大数据工程师","city":"武汉-关山","edu":"本科及以上","salary":"8-15k·12薪","experienceTime":"3-5年","age":"年龄不限","jobUrl":"https://www.liepin.com/job/1932631709.shtml","codeName":"语言不限"},{"name":"java后端开发","city":"上海-浦东新区","edu":"本科及以上","salary":"15-25k·15薪","experienceTime":"1-3年","age":"年龄不限","jobUrl":"https://www.liepin.com/job/1932631153.shtml","codeName":"语言不限"},{"name":"java高级工程师","city":"武汉-江夏区","edu":"统招本科","salary":"10-15k·14薪","experienceTime":"5-10年","age":"年龄不限","jobUrl":"https://www.liepin.com/job/1932630923.shtml","codeName":"语言不限"},{"name":"","city":"","edu":"","salary":"","experienceTime":"","age":"","jobUrl":"https://www.liepin.com/job/1932630103.shtml","codeName":""},{"name":"java开发工程师","city":"西安-高新区","edu":"大专及以上","salary":"5-7k·12薪","experienceTime":"经验不限","age":"年龄不限","jobUrl":"https://www.liepin.com/job/1932629535.shtml","codeName":"语言不限"},{"name":"java开发工程师","city":"苏州-工业园区","edu":"大专及以上","salary":"5-7k·12薪","experienceTime":"经验不限","age":"年龄不限","jobUrl":"https://www.liepin.com/job/1932629533.shtml","codeName":"语言不限"},{"name":"","city":"","edu":"","salary":"","experienceTime":"","age":"","jobUrl":"https://www.liepin.com/job/1932627887.shtml","codeName":""},{"name":"","city":"","edu":"","salary":"","experienceTime":"","age":"","jobUrl":"https://www.liepin.com/job/1932627085.shtml","codeName":""},{"name":"","city":"","edu":"","salary":"","experienceTime":"","age":"","jobUrl":"https://www.liepin.com/job/1932625637.shtml","codeName":""},{"name":"Java-厦门","city":"厦门-思明区","edu":"本科及以上","salary":"10-20k·12薪","experienceTime":"1-3年","age":"年龄不限","jobUrl":"https://www.liepin.com/job/1932623867.shtml","codeName":"语言不限"},{"name":"java开发工程师","city":"成都","edu":"统招本科","salary":"10-20k·15薪","experienceTime":"3-5年","age":"年龄不限","jobUrl":"https://www.liepin.com/job/1932623251.shtml","codeName":"语言不限"},{"name":"","city":"","edu":"","salary":"","experienceTime":"","age":"","jobUrl":"https://www.liepin.com/job/1932622845.shtml","codeName":""},{"name":"高级软件工程师（JAVA）","city":"深圳","edu":"本科及以上","salary":"18-22k·12薪","experienceTime":"5-10年","age":"年龄不限","jobUrl":"https://www.liepin.com/job/1932622045.shtml","codeName":"普通话"},{"name":"高级java开发工程师","city":"青岛","edu":"本科及以上","salary":"15-20k·12薪","experienceTime":"5-10年","age":"年龄不限","jobUrl":"https://www.liepin.com/job/1932621777.shtml","codeName":"语言不限"},{"name":"JAVA软件工程师(J10492)","city":"上海","edu":"本科及以上","salary":"15-20k·12薪","experienceTime":"3-5年","age":"年龄不限","jobUrl":"https://www.liepin.com/job/1932618701.shtml","codeName":"普通话"},{"name":"","city":"","edu":"","salary":"","experienceTime":"","age":"","jobUrl":"https://www.liepin.com/job/1932615557.shtml","codeName":""},{"name":"游戏JAVA服务器主程","city":"北京","edu":"本科及以上","salary":"25-45k·12薪","experienceTime":"5-10年","age":"年龄不限","jobUrl":"https://www.liepin.com/job/1932615437.shtml","codeName":"语言不限"},{"name":"","city":"","edu":"","salary":"","experienceTime":"","age":"","jobUrl":"https://www.liepin.com/job/1932614055.shtml","codeName":""},{"name":"","city":"","edu":"","salary":"","experienceTime":"","age":"","jobUrl":"https://www.liepin.com/job/1932613751.shtml","codeName":""},{"name":"中高级JAVA工程师","city":"北京-朝阳区","edu":"统招本科","salary":"13-20k·13薪","experienceTime":"3-5年","age":"年龄不限","jobUrl":"https://www.liepin.com/job/1932610301.shtml","codeName":"语言不限"},{"name":"","city":"","edu":"","salary":"","experienceTime":"","age":"","jobUrl":"https://www.liepin.com/job/1932609621.shtml","codeName":""},{"name":"","city":"","edu":"","salary":"","experienceTime":"","age":"","jobUrl":"https://www.liepin.com/job/1932608613.shtml","codeName":""},{"name":"","city":"","edu":"","salary":"","experienceTime":"","age":"","jobUrl":"https://www.liepin.com/job/1932608233.shtml","codeName":""},{"name":"对日JAVA开发工程师（J10387）","city":"上海-赵巷","edu":"大专及以上","salary":"10-15k·12薪","experienceTime":"1-3年","age":"年龄不限","jobUrl":"https://www.liepin.com/job/1932604067.shtml","codeName":"语言不限"},{"name":"Java+PHP开发工程师","city":"上海","edu":"大专及以上","salary":"15-20k·12薪","experienceTime":"5-10年","age":"年龄不限","jobUrl":"https://www.liepin.com/job/1932602347.shtml","codeName":"语言不限"},{"name":"java开发经理-03","city":"深圳-大冲","edu":"大专及以上","salary":"25-35k·13薪","experienceTime":"5-10年","age":"年龄不限","jobUrl":"https://www.liepin.com/job/1932601295.shtml","codeName":"语言不限"},{"name":"","city":"","edu":"","salary":"","experienceTime":"","age":"","jobUrl":"https://www.liepin.com/job/1932600993.shtml","codeName":""},{"name":"JAVA架构师","city":"上海","edu":"本科及以上","salary":"30-50k·14薪","experienceTime":"5-10年","age":"年龄不限","jobUrl":"https://www.liepin.com/job/1932600793.shtml","codeName":"语言不限"},{"name":"java开发","city":"杭州-西溪","edu":"大专及以上","salary":"12-20k·12薪","experienceTime":"3-5年","age":"年龄不限","jobUrl":"https://www.liepin.com/job/1932598289.shtml","codeName":"语言不限"},{"name":"java","city":"杭州-余杭区","edu":"大专及以上","salary":"12-20k·12薪","experienceTime":"3-5年","age":"年龄不限","jobUrl":"https://www.liepin.com/job/1932598163.shtml","codeName":"语言不限"},{"name":"","city":"","edu":"","salary":"","experienceTime":"","age":"","jobUrl":"https://www.liepin.com/job/1932597241.shtml","codeName":""},{"name":"","city":"","edu":"","salary":"","experienceTime":"","age":"","jobUrl":"https://www.liepin.com/job/1932596491.shtml","codeName":""},{"name":"java开发工程师","city":"嘉兴","edu":"本科及以上","salary":"8-15k·12薪","experienceTime":"5-10年","age":"年龄不限","jobUrl":"https://www.liepin.com/job/1932596175.shtml","codeName":"语言不限"},{"name":"Java工程师（驻场  外派）","city":"北京-上地","edu":"本科及以上","salary":"15-25k·12薪","experienceTime":"3-5年","age":"年龄不限","jobUrl":"https://www.liepin.com/job/1932593443.shtml","codeName":"语言不限"},{"name":"Java工程师（需出差：苏州）","city":"北京","edu":"本科及以上","salary":"13-20k·12薪","experienceTime":"3-5年","age":"年龄不限","jobUrl":"https://www.liepin.com/job/1932593307.shtml","codeName":"语言不限"},{"name":"高级java开发工程师","city":"广州-海珠区","edu":"大专及以上","salary":"15-25k·12薪","experienceTime":"3-5年","age":"年龄不限","jobUrl":"https://www.liepin.com/job/1932591205.shtml","codeName":"语言不限"},{"name":"Java开发工程师","city":"北京","edu":"本科及以上","salary":"18-23k·12薪","experienceTime":"5-10年","age":"年龄不限","jobUrl":"https://www.liepin.com/job/1932590223.shtml","codeName":"语言不限"},{"name":"","city":"","edu":"","salary":"","experienceTime":"","age":"","jobUrl":"https://www.liepin.com/job/1932589375.shtml","codeName":""},{"name":"","city":"","edu":"","salary":"","experienceTime":"","age":"","jobUrl":"https://www.liepin.com/job/1932589189.shtml","codeName":""},{"name":"Java","city":"上海-浦东新区","edu":"本科及以上","salary":"9-11k·12薪","experienceTime":"1-3年","age":"年龄不限","jobUrl":"https://www.liepin.com/job/1932588553.shtml","codeName":"语言不限"},{"name":"Java开发工程师（苏州-AI-智能平台）","city":"苏州-花桥","edu":"本科及以上","salary":"15-30k·12薪","experienceTime":"5-10年","age":"年龄不限","jobUrl":"https://www.liepin.com/job/1932587983.shtml","codeName":"语言不限"},{"name":"企平-Java开发技术专家","city":"上海-长宁区","edu":"本科及以上","salary":"20-35k·15薪","experienceTime":"5-10年","age":"年龄不限","jobUrl":"https://www.liepin.com/job/1932587149.shtml","codeName":"语言不限"},{"name":"java开发工程师","city":"广州-黄埔区","edu":"大专及以上","salary":"10-15k·12薪","experienceTime":"1-3年","age":"年龄不限","jobUrl":"https://www.liepin.com/job/1932586281.shtml","codeName":"语言不限"},{"name":"","city":"","edu":"","salary":"","experienceTime":"","age":"","jobUrl":"https://www.liepin.com/job/1932586131.shtml","codeName":""},{"name":"","city":"","edu":"","salary":"","experienceTime":"","age":"","jobUrl":"https://www.liepin.com/job/1932585407.shtml","codeName":""},{"name":"","city":"","edu":"","salary":"","experienceTime":"","age":"","jobUrl":"https://www.liepin.com/job/1932585005.shtml","codeName":""},{"name":"Java开发工程师","city":"成都-高新区","edu":"本科及以上","salary":"12-20k·12薪","experienceTime":"5-10年","age":"年龄不限","jobUrl":"https://www.liepin.com/job/1932582737.shtml","codeName":"普通话"},{"name":"Java技术专家","city":"杭州-滨江区","edu":"统招本科","salary":"15-25k·15薪","experienceTime":"5-10年","age":"年龄不限","jobUrl":"https://www.liepin.com/job/1932577451.shtml","codeName":"语言不限"},{"name":"JAVA架构师（Agent方向）","city":"北京","edu":"统招本科","salary":"25-50k·14薪","experienceTime":"5-10年","age":"年龄不限","jobUrl":"https://www.liepin.com/job/1932577299.shtml","codeName":"语言不限"},{"name":"Java","city":"深圳","edu":"统招本科","salary":"20-40k·13薪","experienceTime":"3-5年","age":"年龄不限","jobUrl":"https://www.liepin.com/job/1932575665.shtml","codeName":"语言不限"},{"name":"java后端工程师","city":"北京","edu":"统招本科","salary":"15-30k·12薪","experienceTime":"3-5年","age":"年龄不限","jobUrl":"https://www.liepin.com/job/1932575279.shtml","codeName":"语言不限"},{"name":"","city":"","edu":"","salary":"","experienceTime":"","age":"","jobUrl":"https://www.liepin.com/job/1932575065.shtml","codeName":""},{"name":"高级java开发工程师","city":"上海","edu":"统招本科","salary":"25-45k·12薪","experienceTime":"3-5年","age":"25-35岁","jobUrl":"https://www.liepin.com/job/1932574561.shtml","codeName":"语言不限"},{"name":"java开发工程师-云计算","city":"杭州-西湖区","edu":"本科及以上","salary":"15-25k·12薪","experienceTime":"3-5年","age":"年龄不限","jobUrl":"https://www.liepin.com/job/1932574365.shtml","codeName":"语言不限"},{"name":"java高级工程师","city":"北京-朝阳区","edu":"本科及以上","salary":"15-20k·12薪","experienceTime":"3-5年","age":"年龄不限","jobUrl":"https://www.liepin.com/job/1932573589.shtml","codeName":"语言不限"},{"name":"","city":"","edu":"","salary":"","experienceTime":"","age":"","jobUrl":"https://www.liepin.com/job/1932573285.shtml","codeName":""},{"name":"资深java开发工程师","city":"杭州-余杭区","edu":"本科及以上","salary":"20-40k·15薪","experienceTime":"5-10年","age":"年龄不限","jobUrl":"https://www.liepin.com/job/1932572955.shtml","codeName":"语言不限"},{"name":"高级Java工程师-云打印方向","city":"北京-朝阳区","edu":"本科及以上","salary":"35-55k·16薪","experienceTime":"3-5年","age":"年龄不限","jobUrl":"https://www.liepin.com/job/1932570403.shtml","codeName":"语言不限"},{"name":"java开发工程师","city":"重庆-杨家坪","edu":"统招本科","salary":"6-8k·13薪","experienceTime":"1-3年","age":"年龄不限","jobUrl":"https://www.liepin.com/job/1932569165.shtml","codeName":"语言不限"},{"name":"java开发工程师","city":"上海-浦东新区","edu":"大专及以上","salary":"10-17k·12薪","experienceTime":"3-5年","age":"年龄不限","jobUrl":"https://www.liepin.com/job/1932566833.shtml","codeName":"语言不限"},{"name":"高级java开发专家（中间件）","city":"杭州-江干区","edu":"大专及以上","salary":"25-38k·12薪","experienceTime":"5-10年","age":"年龄不限","jobUrl":"https://www.liepin.com/job/1932565561.shtml","codeName":"语言不限"},{"name":"","city":"","edu":"","salary":"","experienceTime":"","age":"","jobUrl":"https://www.liepin.com/job/1932564539.shtml","codeName":""},{"name":"java开发工程师","city":"重庆","edu":"统招本科","salary":"面议","experienceTime":"5-10年","age":"年龄不限","jobUrl":"https://www.liepin.com/job/1932562243.shtml","codeName":"语言不限"},{"name":"","city":"","edu":"","salary":"","experienceTime":"","age":"","jobUrl":"https://www.liepin.com/job/1932561979.shtml","codeName":""},{"name":"","city":"","edu":"","salary":"","experienceTime":"","age":"","jobUrl":"https://www.liepin.com/job/1932561969.shtml","codeName":""},{"name":"高级java工程师","city":"北京-朝阳区","edu":"本科及以上","salary":"15-25k·15薪","experienceTime":"3-5年","age":"年龄不限","jobUrl":"https://www.liepin.com/job/1932560939.shtml","codeName":"语言不限"},{"name":"","city":"","edu":"","salary":"","experienceTime":"","age":"","jobUrl":"https://www.liepin.com/job/1932559117.shtml","codeName":""},{"name":"java架构师","city":"北京-海淀区","edu":"统招本科","salary":"20-40k·14薪","experienceTime":"5-10年","age":"30-35岁","jobUrl":"https://www.liepin.com/job/1932558235.shtml","codeName":"语言不限"},{"name":"java开发工程师","city":"北京-海淀区","edu":"统招本科","salary":"20-30k·14薪","experienceTime":"3-5年","age":"25-35岁","jobUrl":"https://www.liepin.com/job/1932558015.shtml","codeName":"语言不限"},{"name":"","city":"","edu":"","salary":"","experienceTime":"","age":"","jobUrl":"https://www.liepin.com/job/1932556991.shtml","codeName":""},{"name":"JAVA技术经理","city":"北京-望京","edu":"大专及以上","salary":"20-25k·12薪","experienceTime":"5-10年","age":"年龄不限","jobUrl":"https://www.liepin.com/job/1932556487.shtml","codeName":"语言不限"},{"name":"","city":"","edu":"","salary":"","experienceTime":"","age":"","jobUrl":"https://www.liepin.com/job/1932556391.shtml","codeName":""},{"name":"","city":"","edu":"","salary":"","experienceTime":"","age":"","jobUrl":"https://www.liepin.com/job/1932556347.shtml","codeName":""},{"name":"JAVA技术（J10594）","city":"济南","edu":"本科及以上","salary":"8-12k·12薪","experienceTime":"1-3年","age":"年龄不限","jobUrl":"https://www.liepin.com/job/1932555683.shtml","codeName":"语言不限"},{"name":"","city":"","edu":"","salary":"","experienceTime":"","age":"","jobUrl":"https://www.liepin.com/job/1932554753.shtml","codeName":""},{"name":"","city":"","edu":"","salary":"","experienceTime":"","age":"","jobUrl":"https://www.liepin.com/job/1932554659.shtml","codeName":""},{"name":"","city":"","edu":"","salary":"","experienceTime":"","age":"","jobUrl":"https://www.liepin.com/job/1932551921.shtml","codeName":""},{"name":"","city":"","edu":"","salary":"","experienceTime":"","age":"","jobUrl":"https://www.liepin.com/job/1932551797.shtml","codeName":""},{"name":"java工程师","city":"成都-高新区","edu":"本科及以上","salary":"10-15k·16薪","experienceTime":"3-5年","age":"年龄不限","jobUrl":"https://www.liepin.com/job/1932551463.shtml","codeName":"语言不限"},{"name":"","city":"","edu":"","salary":"","experienceTime":"","age":"","jobUrl":"https://www.liepin.com/job/1932550893.shtml","codeName":""},{"name":"高级Java研发工程师（大数据产品方向）","city":"上海","edu":"本科及以上","salary":"15-30k·13薪","experienceTime":"3-5年","age":"年龄不限","jobUrl":"https://www.liepin.com/job/1932550835.shtml","codeName":"语言不限"},{"name":"","city":"","edu":"","salary":"","experienceTime":"","age":"","jobUrl":"https://www.liepin.com/job/1932550747.shtml","codeName":""},{"name":"Java技术","city":"长沙","edu":"本科及以上","salary":"8-12k·12薪","experienceTime":"1-3年","age":"年龄不限","jobUrl":"https://www.liepin.com/job/1932550653.shtml","codeName":"语言不限"},{"name":"","city":"","edu":"","salary":"","experienceTime":"","age":"","jobUrl":"https://www.liepin.com/job/1932550583.shtml","codeName":""},{"name":"java工程师","city":"上海","edu":"本科及以上","salary":"16-21k·12薪","experienceTime":"1-3年","age":"年龄不限","jobUrl":"https://www.liepin.com/job/1932550043.shtml","codeName":"语言不限"},{"name":"","city":"","edu":"","salary":"","experienceTime":"","age":"","jobUrl":"https://www.liepin.com/job/1932548357.shtml","codeName":""},{"name":"Java Architect 应用架构师","city":"深圳-东门","edu":"本科及以上","salary":"30-40k·12薪","experienceTime":"5-10年","age":"年龄不限","jobUrl":"https://www.liepin.com/job/1932548163.shtml","codeName":"语言不限"},{"name":"","city":"","edu":"","salary":"","experienceTime":"","age":"","jobUrl":"https://www.liepin.com/job/1932546517.shtml","codeName":""},{"name":"java开发工程师","city":"郑州-郑东新区","edu":"统招本科","salary":"8-10k·12薪","experienceTime":"1-3年","age":"年龄不限","jobUrl":"https://www.liepin.com/job/1932545425.shtml","codeName":"语言不限"},{"name":"Java开发工程师 (MJ003323)","city":"广州-番禺区","edu":"本科及以上","salary":"20-40k·13薪","experienceTime":"3-5年","age":"年龄不限","jobUrl":"https://www.liepin.com/job/1932543235.shtml","codeName":"语言不限"},{"name":"java工程师","city":"杭州-西湖区","edu":"统招本科","salary":"13-25k·12薪","experienceTime":"3-5年","age":"年龄不限","jobUrl":"https://www.liepin.com/job/1932541769.shtml","codeName":"语言不限"},{"name":"Java工程师","city":"上海-闵行区","edu":"大专及以上","salary":"10-18k·14薪","experienceTime":"3-5年","age":"年龄不限","jobUrl":"https://www.liepin.com/job/1932533671.shtml","codeName":"语言不限"},{"name":"Java","city":"杭州","edu":"本科及以上","salary":"20-40k·18薪","experienceTime":"3-5年","age":"年龄不限","jobUrl":"https://www.liepin.com/job/1932532171.shtml","codeName":"语言不限"},{"name":"高级java开发工程师","city":"北京-西城区","edu":"统招本科","salary":"25-50k·13薪","experienceTime":"3-5年","age":"年龄不限","jobUrl":"https://www.liepin.com/job/1932529435.shtml","codeName":"语言不限"},{"name":"","city":"","edu":"","salary":"","experienceTime":"","age":"","jobUrl":"https://www.liepin.com/job/1932529311.shtml","codeName":""},{"name":"","city":"","edu":"","salary":"","experienceTime":"","age":"","jobUrl":"https://www.liepin.com/job/1932526317.shtml","codeName":""},{"name":"","city":"","edu":"","salary":"","experienceTime":"","age":"","jobUrl":"https://www.liepin.com/job/1932523827.shtml","codeName":""},{"name":"","city":"","edu":"","salary":"","experienceTime":"","age":"","jobUrl":"https://www.liepin.com/job/1932521583.shtml","codeName":""},{"name":"","city":"","edu":"","salary":"","experienceTime":"","age":"","jobUrl":"https://www.liepin.com/job/1932519097.shtml","codeName":""},{"name":"","city":"","edu":"","salary":"","experienceTime":"","age":"","jobUrl":"https://www.liepin.com/job/1932517707.shtml","codeName":""},{"name":"","city":"","edu":"","salary":"","experienceTime":"","age":"","jobUrl":"https://www.liepin.com/job/1932510889.shtml","codeName":""},{"name":"中高级JAVA开发工程师","city":"北京","edu":"统招本科","salary":"15-30k·14薪","experienceTime":"3-5年","age":"年龄不限","jobUrl":"https://www.liepin.com/job/1932510473.shtml","codeName":"语言不限"},{"name":"","city":"","edu":"","salary":"","experienceTime":"","age":"","jobUrl":"https://www.liepin.com/job/1932510039.shtml","codeName":""},{"name":"","city":"","edu":"","salary":"","experienceTime":"","age":"","jobUrl":"https://www.liepin.com/job/1932507865.shtml","codeName":""},{"name":"java开发工程师（苏州）","city":"苏州-工业园区","edu":"大专及以上","salary":"10-20k·12薪","experienceTime":"3-5年","age":"年龄不限","jobUrl":"https://www.liepin.com/job/1932507415.shtml","codeName":"语言不限"},{"name":"","city":"","edu":"","salary":"","experienceTime":"","age":"","jobUrl":"https://www.liepin.com/job/1932507325.shtml","codeName":""},{"name":"","city":"","edu":"","salary":"","experienceTime":"","age":"","jobUrl":"https://www.liepin.com/job/1932507089.shtml","codeName":""},{"name":"","city":"","edu":"","salary":"","experienceTime":"","age":"","jobUrl":"https://www.liepin.com/job/1932506759.shtml","codeName":""},{"name":"高级Java开发工程师","city":"南京-尧化","edu":"本科及以上","salary":"20-35k·14薪","experienceTime":"5-10年","age":"年龄不限","jobUrl":"https://www.liepin.com/job/1932506523.shtml","codeName":"语言不限"},{"name":"Java中高级工程师","city":"佛山","edu":"本科及以上","salary":"15-20k·12薪","experienceTime":"5-10年","age":"年龄不限","jobUrl":"https://www.liepin.com/job/1932500915.shtml","codeName":"普通话"},{"name":"","city":"","edu":"","salary":"","experienceTime":"","age":"","jobUrl":"https://www.liepin.com/job/1932497717.shtml","codeName":""},{"name":"","city":"","edu":"","salary":"","experienceTime":"","age":"","jobUrl":"https://www.liepin.com/job/1932497685.shtml","codeName":""},{"name":"Java开发工程师","city":"深圳","edu":"本科及以上","salary":"20-25k·12薪","experienceTime":"3-5年","age":"年龄不限","jobUrl":"https://www.liepin.com/job/1932497493.shtml","codeName":"语言不限"},{"name":"","city":"","edu":"","salary":"","experienceTime":"","age":"","jobUrl":"https://www.liepin.com/job/1932496359.shtml","codeName":""},{"name":"Java架构师-报告报表方向","city":"北京","edu":"本科及以上","salary":"30-50k·13薪","experienceTime":"5-10年","age":"年龄不限","jobUrl":"https://www.liepin.com/job/1932496355.shtml","codeName":"语言不限"},{"name":"java开发工程师","city":"武汉-洪山区","edu":"本科及以上","salary":"9-11k·12薪","experienceTime":"1-3年","age":"年龄不限","jobUrl":"https://www.liepin.com/job/1932493337.shtml","codeName":"语言不限"},{"name":"","city":"","edu":"","salary":"","experienceTime":"","age":"","jobUrl":"https://www.liepin.com/job/1932484315.shtml","codeName":""},{"name":"高级java工程师","city":"北京-海淀区","edu":"统招本科","salary":"20-30k·12薪","experienceTime":"3-5年","age":"25-35岁","jobUrl":"https://www.liepin.com/job/1932481521.shtml","codeName":"英语 + 普通话"},{"name":"","city":"","edu":"","salary":"","experienceTime":"","age":"","jobUrl":"https://www.liepin.com/job/1932481129.shtml","codeName":""},{"name":"Java开发工程师（SAAS系统）","city":"上海-徐汇区","edu":"大专及以上","salary":"12-18k·12薪","experienceTime":"3-5年","age":"年龄不限","jobUrl":"https://www.liepin.com/job/1932478631.shtml","codeName":"语言不限"},{"name":"","city":"","edu":"","salary":"","experienceTime":"","age":"","jobUrl":"https://www.liepin.com/job/1932477173.shtml","codeName":""},{"name":"","city":"","edu":"","salary":"","experienceTime":"","age":"","jobUrl":"https://www.liepin.com/job/1932476475.shtml","codeName":""},{"name":"","city":"","edu":"","salary":"","experienceTime":"","age":"","jobUrl":"https://www.liepin.com/job/1932475699.shtml","codeName":""},{"name":"","city":"","edu":"","salary":"","experienceTime":"","age":"","jobUrl":"https://www.liepin.com/job/1932475621.shtml","codeName":""},{"name":"","city":"","edu":"","salary":"","experienceTime":"","age":"","jobUrl":"https://www.liepin.com/job/1932472809.shtml","codeName":""},{"name":"Java后端高级开发工程师","city":"成都","edu":"本科及以上","salary":"12-18k·13薪","experienceTime":"3-5年","age":"年龄不限","jobUrl":"https://www.liepin.com/job/1932471499.shtml","codeName":"语言不限"},{"name":"","city":"","edu":"","salary":"","experienceTime":"","age":"","jobUrl":"https://www.liepin.com/job/1932470491.shtml","codeName":""},{"name":"Java开发工程师（运维工具研发岗024应届）","city":"上海-浦东新区","edu":"本科及以上","salary":"15-25k·12薪","experienceTime":"经验不限","age":"年龄不限","jobUrl":"https://www.liepin.com/job/1932469303.shtml","codeName":"语言不限"},{"name":"","city":"","edu":"","salary":"","experienceTime":"","age":"","jobUrl":"https://www.liepin.com/job/1932469189.shtml","codeName":""},{"name":"java开发工程师","city":"北京","edu":"大专及以上","salary":"10-20k·12薪","experienceTime":"5-10年","age":"年龄不限","jobUrl":"https://www.liepin.com/job/1932466697.shtml","codeName":"语言不限"},{"name":"","city":"","edu":"","salary":"","experienceTime":"","age":"","jobUrl":"https://www.liepin.com/job/1932463563.shtml","codeName":""},{"name":"","city":"","edu":"","salary":"","experienceTime":"","age":"","jobUrl":"https://www.liepin.com/job/1932463237.shtml","codeName":""},{"name":"java中级开发工程师","city":"长春-朝阳区","edu":"大专及以上","salary":"8-15k·12薪","experienceTime":"3-5年","age":"年龄不限","jobUrl":"https://www.liepin.com/job/1932462889.shtml","codeName":"语言不限"},{"name":"","city":"","edu":"","salary":"","experienceTime":"","age":"","jobUrl":"https://www.liepin.com/job/1932462681.shtml","codeName":""},{"name":"","city":"","edu":"","salary":"","experienceTime":"","age":"","jobUrl":"https://www.liepin.com/job/1932462525.shtml","codeName":""},{"name":"","city":"","edu":"","salary":"","experienceTime":"","age":"","jobUrl":"https://www.liepin.com/job/1932462343.shtml","codeName":""},{"name":"Java开发工程师（北京校招）","city":"北京","edu":"本科及以上","salary":"2-4k·12薪","experienceTime":"经验不限","age":"年龄不限","jobUrl":"https://www.liepin.com/job/1932459207.shtml","codeName":"语言不限"},{"name":"JAVA工程师","city":"上海-浦东新区","edu":"统招本科","salary":"8-15k·12薪","experienceTime":"1-3年","age":"年龄不限","jobUrl":"https://www.liepin.com/job/1932457875.shtml","codeName":"语言不限"},{"name":"","city":"","edu":"","salary":"","experienceTime":"","age":"","jobUrl":"https://www.liepin.com/job/1932450841.shtml","codeName":""},{"name":"","city":"","edu":"","salary":"","experienceTime":"","age":"","jobUrl":"https://www.liepin.com/job/1932450747.shtml","codeName":""},{"name":"","city":"","edu":"","salary":"","experienceTime":"","age":"","jobUrl":"https://www.liepin.com/job/1932450619.shtml","codeName":""},{"name":"","city":"","edu":"","salary":"","experienceTime":"","age":"","jobUrl":"https://www.liepin.com/job/1932449765.shtml","codeName":""},{"name":"高级java工程师","city":"上海-陆家嘴","edu":"统招本科","salary":"20-40k·15薪","experienceTime":"5-10年","age":"年龄不限","jobUrl":"https://www.liepin.com/job/1932449741.shtml","codeName":"语言不限"},{"name":"","city":"","edu":"","salary":"","experienceTime":"","age":"","jobUrl":"https://www.liepin.com/job/1932447987.shtml","codeName":""}]